fustor_source_oss/__init__.py
fustor_source_oss/config.py
fustor_source_oss/driver.py
fustor_source_oss/mapper.py
fustor_source_oss-0.2.16.dist-info/METADATA
fustor_source_oss-0.2.16.dist-info/WHEEL
fustor_source_oss-0.2.16.dist-info/entry_points.txt
fustor_source_oss-0.2.16.dist-info/top_level.txt
fustor_source_oss-0.2.16.dist-info/RECORD
