Metadata-Version: 2.4
Name: fustor-source-oss
Version: 0.2.16
Summary: Fustor Source Driver for S3-compatible object storage (OSS)
Requires-Python: >=3.11
Requires-Dist: boto3<2.0.0,>=1.28.0
Requires-Dist: fustor-core
Requires-Dist: pydantic<3.0.0,>=2.0.0
